nr_datasets_metadata/__init__.py
nr_datasets_metadata/constants.py
nr_datasets_metadata/datamodels/__init__.py
nr_datasets_metadata/datamodels/build.sh
nr_datasets_metadata/datamodels/nr-datasets-definitions-v1.0.0.json5
nr_datasets_metadata/datamodels/nr-datasets-metadata-v1.0.0.json5
nr_datasets_metadata/jsonschemas/__init__.py
nr_datasets_metadata/jsonschemas/nr_datasets_metadata/__init__.py
nr_datasets_metadata/jsonschemas/nr_datasets_metadata/nr-datasets-metadata-v3.0.0.json
nr_datasets_metadata/mapping_includes/__init__.py
nr_datasets_metadata/mapping_includes/v7/__init__.py
nr_datasets_metadata/mapping_includes/v7/nr-datasets-metadata-v3.0.0.json
nr_datasets_metadata/mappings/__init__.py
nr_datasets_metadata/mappings/v7/__init__.py
nr_datasets_metadata/marshmallow/__init__.py
nr_datasets_metadata/marshmallow/constants.py
nr_datasets_metadata/marshmallow/subschemas/__init__.py
nr_datasets_metadata/marshmallow/subschemas/authority.py
nr_datasets_metadata/marshmallow/subschemas/dataset.py
nr_datasets_metadata/marshmallow/subschemas/date.py
nr_datasets_metadata/marshmallow/subschemas/funding.py
nr_datasets_metadata/marshmallow/subschemas/geo.py
nr_datasets_metadata/marshmallow/subschemas/person.py
nr_datasets_metadata/marshmallow/subschemas/pids.py
nr_datasets_metadata/marshmallow/subschemas/related.py
nr_datasets_metadata/marshmallow/subschemas/taxonomy.py
nr_datasets_metadata/marshmallow/subschemas/titles.py
nr_datasets_metadata/marshmallow/subschemas/utils.py
nr_datasets_metadata/record.py
techlib_nr_datasets_metadata-3.1.15.dist-info/entry_points.txt
techlib_nr_datasets_metadata-3.1.15.dist-info/WHEEL
techlib_nr_datasets_metadata-3.1.15.dist-info/METADATA
techlib_nr_datasets_metadata-3.1.15.dist-info/RECORD
