Metadata-Version: 2.1
Name: techlib-nr-datasets-metadata
Version: 3.1.15
Summary: Czech National Repository datasets data model.
License: MIT
Keywords: Czech,Nation,Repository,Invenio,datasets
Author: Miroslav Bauer
Author-email: Miroslav.Bauer@cesnet.cz
Requires-Python: >=3.8,<4.0
Classifier: Development Status :: 3 - Alpha
Classifier: Environment :: Web Environment
Classifier: Intended Audience :: Developers
Classifier: License :: OSI Approved :: MIT License
Classifier: Operating System :: OS Independent
Classifier: Programming Language :: Python
Classifier: Programming Language :: Python :: 3
Classifier: Programming Language :: Python :: 3.7
Classifier: Programming Language :: Python :: 3.8
Classifier: Topic :: Internet :: WWW/HTTP :: Dynamic Content
Classifier: Topic :: Software Development :: Libraries :: Python Modules
Requires-Dist: oarepo (>=3.3,<4.0)
Requires-Dist: oarepo-rdm-records (>=3.2.0,<4.0.0)
